stltspref/__init__.py
stltspref/benchmarks.py
stltspref/constants.py
stltspref/linear_expression.py
stltspref/main_constraints.py
stltspref/milp_helper.py
stltspref/preferential_synthesis.py
stltspref/problem.py
stltspref/result_helper.py
stltspref/rss_distance.py
stltspref/rss_scenario.py
stltspref/stl.py
stltspref/stl_atomic.py
stltspref/stl_base.py
stltspref/stl_convert.py
stltspref/system_model.py
stltspref/trace.py
stltspref/validator.py
stltspref/visualize.py
stltspref-1.1.0.dist-info/licenses/LICENSE
stltspref-1.1.0.dist-info/METADATA
stltspref-1.1.0.dist-info/WHEEL
stltspref-1.1.0.dist-info/top_level.txt
stltspref-1.1.0.dist-info/RECORD
