Metadata-Version: 2.4
Name: stltspref
Version: 1.1.0
Summary: An MILP-based tool for generating diverse traces of execution of a model that satisfy a specification, as well as corner-cases.
Author-email: Martin Jouve-Genty <martin.jouve-genty@ens-lyon.fr>, Sota Sato <sotasato@nii.ac.jp>
Project-URL: Code, https://gitlab.aliens-lyon.fr/mjouvege/stltspref
Requires-Python: >=3.8
License-File: LICENSE
Requires-Dist: numpy>=2.3.3
Requires-Dist: gurobipy>=11.0.0
Requires-Dist: scipy>=1.16.2
Requires-Dist: matplotlib>=3.10.6
Requires-Dist: pandas>=2.3.3
Requires-Dist: plotly>=5.20.0
Provides-Extra: dev
Requires-Dist: pytest; extra == "dev"
Requires-Dist: flake8; extra == "dev"
Requires-Dist: mypy; extra == "dev"
Requires-Dist: black; extra == "dev"
Requires-Dist: isort; extra == "dev"
Dynamic: license-file
